ndacrawler/__init__.py
ndacrawler/_internal_utils.py
ndacrawler/drugs.py
ndacrawler/extractors/__init__.py
ndacrawler/extractors/drug_shops.py
ndacrawler/extractors/pharmacies.py
ndacrawler-0.1.1.dist-info/LICENSE
ndacrawler-0.1.1.dist-info/METADATA
ndacrawler-0.1.1.dist-info/WHEEL
ndacrawler-0.1.1.dist-info/top_level.txt
ndacrawler-0.1.1.dist-info/RECORD
