Metadata-Version: 2.1
Name: ndacrawler
Version: 0.1.1
Summary: A simple crawler for the NDA website
Home-page: https://github.com/AntonioMande/ndacrawler
Author: Antonio Mande
Author-email: mandetonny@gmail.com
License: UNKNOWN
Platform: UNKNOWN
Classifier: Programming Language :: Python :: 3
Classifier: License :: OSI Approved :: MIT License
Classifier: Operating System :: OS Independent
Requires-Python: >=3.6
License-File: LICENSE
Requires-Dist: requests
Requires-Dist: beautifulsoup4 (==4.10)
Requires-Dist: lxml
Requires-Dist: cchardet
